{
  "actualizado": "2026-04-23 18:37:18",
  "kpis": {
    "nivel_l": 11.61,
    "humedad_pct": 84.0,
    "temp_c": 19.1,
    "punto_rocio_c": 16.3,
    "presion_inhg": 24.929,
    "viento_kmh": 0.0,
    "viento_dir_deg": 347.0,
    "lluvia_hora_mm": 0.0,
    "radiacion_solar_wm2": 0.0,
    "uv": 0.0
  },
  "sistema": {
    "cpu_temp_c": 34.5,
    "voltaje_v": 0.88,
    "ram_uso_pct": 10.0,
    "disco_uso_pct": 10.3,
    "uptime": "7h 1m"
  },
  "series": {
    "labels": [
      "18:12",
      "18:13",
      "18:15",
      "18:16",
      "18:17",
      "18:18",
      "18:19",
      "18:20",
      "18:21",
      "18:22",
      "18:23",
      "18:24",
      "18:25",
      "18:26",
      "18:27",
      "18:28",
      "18:29",
      "18:30",
      "18:31",
      "18:32",
      "18:33",
      "18:34",
      "18:35",
      "18:36"
    ],
    "nivel_l": [
      1.36,
      2.2,
      4.08,
      4.39,
      4.39,
      4.44,
      4.44,
      4.5,
      4.5,
      7.01,
      6.95,
      6.9,
      6.9,
      6.9,
      6.9,
      9.31,
      9.36,
      9.36,
      9.36,
      9.36,
      15.58,
      15.58,
      11.61,
      11.61
    ],
    "humedad_pct": [
      81.0,
      82.0,
      82.0,
      83.0,
      82.0,
      82.0,
      83.0,
      82.0,
      82.0,
      83.0,
      83.0,
      84.0,
      85.0,
      85.0,
      85.0,
      84.0,
      84.0,
      85.0,
      85.0,
      85.0,
      85.0,
      85.0,
      84.0,
      84.0
    ],
    "temp_c": [
      19.7,
      19.7,
      19.6,
      19.6,
      19.6,
      19.6,
      19.6,
      19.6,
      19.5,
      19.5,
      19.5,
      19.5,
      19.5,
      19.4,
      19.4,
      19.4,
      19.3,
      19.3,
      19.3,
      19.2,
      19.2,
      19.2,
      19.1,
      19.1
    ],
    "punto_rocio_c": [
      16.3,
      16.5,
      16.4,
      16.7,
      16.4,
      16.4,
      16.7,
      16.4,
      16.3,
      16.6,
      16.6,
      16.7,
      16.9,
      16.8,
      16.8,
      16.6,
      16.5,
      16.7,
      16.7,
      16.6,
      16.6,
      16.6,
      16.3,
      16.3
    ],
    "presion_inhg": [
      24.932,
      24.929,
      24.929,
      24.929,
      24.929,
      24.932,
      24.926,
      24.932,
      24.929,
      24.935,
      24.929,
      24.923,
      24.926,
      24.923,
      24.917,
      24.92,
      24.926,
      24.926,
      24.923,
      24.926,
      24.929,
      24.932,
      24.923,
      24.929
    ],
    "viento_kmh": [
      0.0,
      0.0,
      0.0,
      0.0,
      0.0,
      0.0,
      0.0,
      0.0,
      0.0,
      0.0,
      0.0,
      0.0,
      0.0,
      0.0,
      0.0,
      0.0,
      0.0,
      0.0,
      0.0,
      0.0,
      0.0,
      0.0,
      0.0,
      0.0
    ],
    "viento_dir_deg": [
      347.0,
      347.0,
      347.0,
      347.0,
      347.0,
      347.0,
      347.0,
      347.0,
      347.0,
      347.0,
      347.0,
      347.0,
      347.0,
      347.0,
      347.0,
      347.0,
      347.0,
      347.0,
      347.0,
      347.0,
      347.0,
      347.0,
      347.0,
      347.0
    ],
    "lluvia_hora_mm": [
      0.0,
      0.0,
      0.0,
      0.0,
      0.0,
      0.0,
      0.0,
      0.0,
      0.0,
      0.0,
      0.0,
      0.0,
      0.0,
      0.0,
      0.0,
      0.0,
      0.0,
      0.0,
      0.0,
      0.0,
      0.0,
      0.0,
      0.0,
      0.0
    ],
    "radiacion_solar_wm2": [
      0.0,
      0.0,
      0.0,
      0.0,
      0.0,
      0.0,
      0.0,
      0.0,
      0.0,
      0.0,
      0.0,
      0.0,
      0.0,
      0.0,
      0.0,
      0.0,
      0.0,
      0.0,
      0.0,
      0.0,
      0.0,
      0.0,
      0.0,
      0.0
    ],
    "uv": [
      0.0,
      0.0,
      0.0,
      0.0,
      0.0,
      0.0,
      0.0,
      0.0,
      0.0,
      0.0,
      0.0,
      0.0,
      0.0,
      0.0,
      0.0,
      0.0,
      0.0,
      0.0,
      0.0,
      0.0,
      0.0,
      0.0,
      0.0,
      0.0
    ]
  }
}